aiohttp_sendgrid/__init__.py
aiohttp_sendgrid/sendgrid.py
aiohttp_sendgrid-0.0.4.dist-info/DESCRIPTION.rst
aiohttp_sendgrid-0.0.4.dist-info/METADATA
aiohttp_sendgrid-0.0.4.dist-info/RECORD
aiohttp_sendgrid-0.0.4.dist-info/WHEEL
aiohttp_sendgrid-0.0.4.dist-info/metadata.json
aiohttp_sendgrid-0.0.4.dist-info/top_level.txt
