Metadata-Version: 2.0
Name: aiohttp-sendgrid
Version: 0.0.4
Summary: SendGrid mail send API wrapper
Home-page: https://github.com/kurlov/aiohttp-sendgrid
Author: Aleksandr Kurlov
Author-email: sasha.kurlov@yandex.com
License: MIT
Download-URL: https://pypi.python.org/pypi/aiohttp-sendgrid
Keywords: aiohttp sendgrid
Platform: UNKNOWN
Classifier: Development Status :: 3 - Alpha
Classifier: License :: OSI Approved :: MIT License
Classifier: Intended Audience :: Developers
Classifier: Programming Language :: Python
Classifier: Programming Language :: Python :: 3
Classifier: Programming Language :: Python :: 3.5
Classifier: Programming Language :: Python :: 3.6
Classifier: Operating System :: POSIX
Classifier: Operating System :: MacOS :: MacOS X
Classifier: Operating System :: Microsoft :: Windows
Classifier: Topic :: Internet :: WWW/HTTP
Classifier: Topic :: Communications :: Email
Classifier: Topic :: Software Development :: Libraries :: Python Modules
Classifier: Framework :: AsyncIO
Requires-Dist: aiohttp (>=2.3.7)
